contador-estacionamiento/contador-estacionamiento.v
module contador_estacionamiento(
    input wire clk,
    input wire reset,
    input wire auto_entra,
    input wire auto_sale,
    output reg [2:0] count,     // 3 bits 
    output lleno,
    output vacio
);

assign lleno = (count == 3'b111);
assign vacio = (count == 3'b000);

always @(posedge clk or posedge reset) 
begin
    if (reset)
        count <= 0;
    else begin
        if (auto_entra && !lleno)
            count <= count + 1;
        else if (auto_sale && !vacio)
            count <= count - 1;
    end
end

endmodule

contador-estacionamiento/contador-estacionamiento_tb.v
`default_nettype none
`timescale 1ns / 1ps
`define DUMPSTR(x) `"x.vcd`"

module contador_estacionamiento_tb;

    reg clk;
    reg reset;
    reg auto_entra;
    reg auto_sale;
    wire [2:0] count;
    wire lleno;
    wire vacio;

    contador_estacionamiento UUT (
        .clk(clk),
        .reset(reset),
        .auto_entra(auto_entra),
        .auto_sale(auto_sale),
        .count(count),
        .lleno(lleno),
        .vacio(vacio)
    );

    // Generador de reloj
    initial begin
        clk = 0;
        forever #5 clk = ~clk;
    end

    initial begin
        $dumpfile("contador-estacionamiento_tb.vcd");
        $dumpvars(0, contador_estacionamiento_tb);

        reset = 1; auto_entra = 0; auto_sale = 0;
        #10;
        reset = 0;

        // Autos entran
        repeat (8) begin
            auto_entra = 1; auto_sale = 0;
            #10;
        end

        // Intentar entrar cuando esta lleno
        auto_entra = 1; auto_sale = 0;
        #20;

        // Autos salen
        repeat (8) begin
            auto_entra = 0; auto_sale = 1;
            #10;
        end

        // Intentar salir cuando esta vacio
        auto_entra = 0; auto_sale = 1;
        #10;

        reset = 1; auto_sale = 0;
        #10;
        reset = 0;
        #10;
        

        $finish;
    end

endmodule

contador-estacionamiento/contador-estacionamiento_tb.vcd
$date
	Fri Jun 20 15:12:00 2025
$end
$version
	Icarus Verilog
$end
$timescale
	1ps
$end
$scope module contador_estacionamiento_tb $end
$var wire 1 ! vacio $end
$var wire 1 " lleno $end
$var wire 3 # count [2:0] $end
$var reg 1 $ auto_entra $end
$var reg 1 % auto_sale $end
$var reg 1 & clk $end
$var reg 1 ' reset $end
$scope module UUT $end
$var wire 1 $ auto_entra $end
$var wire 1 % auto_sale $end
$var wire 1 & clk $end
$var wire 1 ' reset $end
$var wire 1 ! vacio $end
$var wire 1 " lleno $end
$var reg 3 ( count [2:0] $end
$upscope $end
$upscope $end
$enddefinitions $end
$comment Show the parameter values. $end
$dumpall
$end
#0
$dumpvars
b0 (
1'
0&
0%
0$
b0 #
0"
1!
$end
#5000
1&
#10000
0&
1$
0'
#15000
0!
b1 #
b1 (
1&
#20000
0&
#25000
b10 #
b10 (
1&
#30000
0&
#35000
b11 #
b11 (
1&
#40000
0&
#45000
b100 #
b100 (
1&
#50000
0&
#55000
b101 #
b101 (
1&
#60000
0&
#65000
b110 #
b110 (
1&
#70000
0&
#75000
1"
b111 #
b111 (
1&
#80000
0&
#85000
1&
#90000
0&
#95000
1&
#100000
0&
#105000
1&
#110000
0&
1%
0$
#115000
0"
b110 #
b110 (
1&
#120000
0&
#125000
b101 #
b101 (
1&
#130000
0&
#135000
b100 #
b100 (
1&
#140000
0&
#145000
b11 #
b11 (
1&
#150000
0&
#155000
b10 #
b10 (
1&
#160000
0&
#165000
b1 #
b1 (
1&
#170000
0&
#175000
1!
b0 #
b0 (
1&
#180000
0&
#185000
1&
#190000
0&
#195000
1&
#200000
0&
0%
1'
#205000
1&
#210000
0&
0'
