fsm-sensores/fsm-sensores.v
module fsm_sensores(
    input wire clk,
    input wire reset,
    input wire a,        // sensor a
    input wire b,        // sensor b
    output reg auto_entra,
    output reg auto_sale,
    output reg persona
);

    reg [2:0] estado, next_estado;

    //           Estados                  Logica estados
    localparam EST_INICIAL = 3'b000,
                                       // -ENTRADA-
               E1 = 3'b001,            // piso sensor (a)
               E2 = 3'b010,            // piso ambos sensores a la vez
               E3 = 3'b011,            // piso sensor (b)

                                       // -SALIDA-        
               S1 = 3'b101,            // piso sensor (b)
               S2 = 3'b110,            // piso ambos sensores a la vez
               S3 = 3'b111,            // piso sensor (a)

                                       // -NO ES AUTO-
               P  = 3'b100;            // piso sensor (a) o (b) y despues no piso (ab) juntos

    // Transición de estado (excel)
    always @(*) begin
        next_estado = estado;
        case (estado)
            EST_INICIAL: begin
                if (a & ~b) next_estado = E1;
                else if (~a & b) next_estado = S1;
            end

            E1: begin
                if (a & b) next_estado = E2;
                else if (~a & ~b) next_estado = P;
            end

            E2: begin
                if (~a & b) next_estado = E3;
                else if (~a & ~b) next_estado = P;
            end

            E3: begin
                if (~a & ~b) next_estado = EST_INICIAL;
            end

            S1: begin
                if (a & b) next_estado = S2;
                else if (~a & ~b) next_estado = P;
            end

            S2: begin
                if (a & ~b) next_estado = S3;
                else if (~a & ~b) next_estado = P;
            end

            S3: begin
                if (~a & ~b) next_estado = EST_INICIAL;
            end

            P: begin
                // Desde P siempre volver a estado inicial
                next_estado = EST_INICIAL;
            end
        endcase
    end

    // Registro de estado actual | Logica de salidas
    always @(posedge clk or posedge reset) begin
        if (reset) begin
            estado <= EST_INICIAL;
            auto_entra <= 0;
            auto_sale  <= 0;
            persona    <= 0;
        end
        else begin
            estado <= next_estado;
            auto_entra <= (estado == E3 && next_estado == EST_INICIAL);
            auto_sale  <= (estado == S3 && next_estado == EST_INICIAL);
            // persona    <= ((estado == E1 || estado == E2) && next_estado == P) || ((estado == S1 || estado == S2) && next_estado == P);
            persona <= ((estado == E1 || estado == E2 || estado == S1 || estado == S2) && next_estado == P);
        end
    end

endmodule

fsm-sensores/fsm-sensores_tb.v
`default_nettype none
`timescale 1ns / 1ps
`define DUMPSTR(x) `"x.vcd`"

module fsm_sensores_tb;

    reg clk, reset, a, b;
    wire auto_entra, auto_sale, persona;

    fsm_sensores uut (
        .clk(clk),
        .reset(reset),
        .a(a),
        .b(b),
        .auto_entra(auto_entra),
        .auto_sale(auto_sale),
        .persona(persona)
    );

    // Reloj: 10ns de período
    initial begin
        clk = 0;
        forever #5 clk = ~clk;
    end

    // Tarea: auto entra correctamente (A1 → A2 → A3 → IDLE)
    task paso_auto_entrada;
    begin
        $display("Auto entra");
        a = 1; b = 0; #10;  // A1
        a = 1; b = 1; #10;  // A2
        a = 0; b = 1; #10;  // A3
        a = 0; b = 0; #10;  // IDLE (se detecta auto_entra)
    end
    endtask

    // Tarea: auto sale correctamente (B1 → B2 → B3 → IDLE)
    task paso_auto_salida;
    begin
        $display("Auto sale");
        a = 0; b = 1; #10;  // B1
        a = 1; b = 1; #10;  // B2
        a = 1; b = 0; #10;  // B3
        a = 0; b = 0; #10;  // IDLE (se detecta auto_sale)
    end
    endtask

    // Tarea: persona intenta entrar pero no completa el paso
    task persona_entrada;
    begin
        $display("Persona entra");
        a = 1; b = 0; #10;  // A1
        a = 1; b = 1; #10;  // A2
        a = 0; b = 0; #10;  // -> P (se detecta persona)
        a = 0; b = 0; #10;  // vuelve a IDLE
    end
    endtask

    // Tarea: persona intenta salir pero no completa el paso
    task persona_salida;
    begin
        $display("Persona sale");
        a = 0; b = 1; #10;  // B1
        a = 1; b = 1; #10;  // B2
        a = 0; b = 0; #10;  // -> P (se detecta persona)
        a = 0; b = 0; #10;  // vuelve a IDLE
    end
    endtask

    initial begin
        $dumpfile("fsm-sensores_tb.vcd");
        $dumpvars(0, fsm_sensores_tb);

        a = 0; b = 0; reset = 1; #10;
        reset = 0;

        // 1. Auto entra correctamente
        paso_auto_entrada();

        // 2. Persona intenta entrar (incompleta)
        persona_entrada();

        // 3. Auto sale correctamente
        paso_auto_salida();

        // 4. Persona intenta salir (incompleta)
        persona_salida();

        #20;
        $finish;
    end

endmodule

fsm-sensores/fsm-sensores_tb.vcd
$date
	Sat Jun 21 00:35:42 2025
$end
$version
	Icarus Verilog
$end
$timescale
	1ps
$end
$scope module fsm_sensores_tb $end
$var wire 1 ! persona $end
$var wire 1 " auto_sale $end
$var wire 1 # auto_entra $end
$var reg 1 $ a $end
$var reg 1 % b $end
$var reg 1 & clk $end
$var reg 1 ' reset $end
$scope module uut $end
$var wire 1 $ a $end
$var wire 1 % b $end
$var wire 1 & clk $end
$var wire 1 ' reset $end
$var parameter 3 ( E1 $end
$var parameter 3 ) E2 $end
$var parameter 3 * E3 $end
$var parameter 3 + EST_INICIAL $end
$var parameter 3 , P $end
$var parameter 3 - S1 $end
$var parameter 3 . S2 $end
$var parameter 3 / S3 $end
$var reg 1 # auto_entra $end
$var reg 1 " auto_sale $end
$var reg 3 0 estado [2:0] $end
$var reg 3 1 next_estado [2:0] $end
$var reg 1 ! persona $end
$upscope $end
$scope task paso_auto_entrada $end
$upscope $end
$scope task paso_auto_salida $end
$upscope $end
$scope task persona_entrada $end
$upscope $end
$scope task persona_salida $end
$upscope $end
$upscope $end
$enddefinitions $end
$comment Show the parameter values. $end
$dumpall
b111 /
b110 .
b101 -
b100 ,
b0 +
b11 *
b10 )
b1 (
$end
#0
$dumpvars
b0 1
b0 0
1'
0&
0%
0$
0#
0"
0!
$end
#5000
1&
#10000
b1 1
0&
1$
0'
#15000
b1 0
1&
#20000
b10 1
0&
1%
#25000
b10 0
1&
#30000
b11 1
0&
0$
#35000
b11 0
1&
#40000
b0 1
0&
0%
#45000
1#
b0 0
1&
#50000
b1 1
0&
1$
#55000
0#
b1 0
1&
#60000
b10 1
0&
1%
#65000
b10 0
1&
#70000
b100 1
0&
0%
0$
#75000
b0 1
1!
b100 0
1&
#80000
0&
#85000
0!
b0 0
1&
#90000
b101 1
0&
1%
#95000
b101 0
1&
#100000
b110 1
0&
1$
#105000
b110 0
1&
#110000
b111 1
0&
0%
#115000
b111 0
1&
#120000
b0 1
0&
0$
#125000
1"
b0 0
1&
#130000
b101 1
0&
1%
#135000
0"
b101 0
1&
#140000
b110 1
0&
1$
#145000
b110 0
1&
#150000
b100 1
0&
0%
0$
#155000
b0 1
1!
b100 0
1&
#160000
0&
#165000
0!
b0 0
1&
