contador-estacionamiento/contador-estacionamiento.v
module contador_estacionamiento(
    input wire clk,
    input wire reset,
    input wire auto_entra,
    input wire auto_sale,
    output reg [2:0] count,     // 3 bits 
    output lleno,
    output vacio
);

assign lleno = (count == 3'b111);
assign vacio = (count == 3'b000);

always @(posedge clk or posedge reset) 
begin
    if (reset)
        count <= 0;
    else begin
        if (auto_entra && !lleno)
            count <= count + 1;
        else if (auto_sale && !vacio)
            count <= count - 1;
    end
end

endmodule

fsm-sensores/fsm-sensores.v
module fsm_sensores(
    input wire clk,
    input wire reset,
    input wire a,        // sensor a
    input wire b,        // sensor b
    output reg auto_entra,
    output reg auto_sale,
    output reg persona
);

    reg [2:0] estado, next_estado;

    //           Estados                  Logica estados
    localparam EST_INICIAL = 3'b000,
                                       // -ENTRADA-
               E1 = 3'b001,            // piso sensor (a)
               E2 = 3'b010,            // piso ambos sensores a la vez
               E3 = 3'b011,            // piso sensor (b)

                                       // -SALIDA-        
               S1 = 3'b101,            // piso sensor (b)
               S2 = 3'b110,            // piso ambos sensores a la vez
               S3 = 3'b111,            // piso sensor (a)

                                       // -NO ES AUTO-
               P  = 3'b100;            // piso sensor (a) o (b) y despues no piso (ab) juntos

    // Transición de estado (excel)
    always @(*) begin
        next_estado = estado;
        case (estado)
            EST_INICIAL: begin
                if (a & ~b) next_estado = E1;
                else if (~a & b) next_estado = S1;
            end

            E1: begin
                if (a & b) next_estado = E2;
                else if (~a & ~b) next_estado = P;
            end

            E2: begin
                if (~a & b) next_estado = E3;
                else if (~a & ~b) next_estado = P;
            end

            E3: begin
                if (~a & ~b) next_estado = EST_INICIAL;
            end

            S1: begin
                if (a & b) next_estado = S2;
                else if (~a & ~b) next_estado = P;
            end

            S2: begin
                if (a & ~b) next_estado = S3;
                else if (~a & ~b) next_estado = P;
            end

            S3: begin
                if (~a & ~b) next_estado = EST_INICIAL;
            end

            P: begin
                // Desde P siempre volver a estado inicial
                next_estado = EST_INICIAL;
            end
        endcase
    end

    // Registro de estado actual | Logica de salidas
    always @(posedge clk or posedge reset) begin
        if (reset) begin
            estado <= EST_INICIAL;
            auto_entra <= 0;
            auto_sale  <= 0;
            persona    <= 0;
        end
        else begin
            estado <= next_estado;
            auto_entra <= (estado == E3 && next_estado == EST_INICIAL);
            auto_sale  <= (estado == S3 && next_estado == EST_INICIAL);
            // persona    <= ((estado == E1 || estado == E2) && next_estado == P) || ((estado == S1 || estado == S2) && next_estado == P);
            persona <= ((estado == E1 || estado == E2 || estado == S1 || estado == S2) && next_estado == P);
        end
    end

endmodule

top-module/top-module.v
`include "../fsm-sensores/fsm-sensores.v"
`include "../contador-estacionamiento/contador-estacionamiento.v"

module top_estacionamiento(
    input wire clk,
    input wire reset,
    input wire btnA,        // Sensor A (botón físico)
    input wire btnB,        // Sensor B (botón físico)
    output wire [3:0] leds  // leds[3]=lleno, leds[2:0]=contador
);
    // vi algo de los botones logica de antirebote
    wire rts, A, B;
    assign rst = ~reset;
    assign A = ~btnA;
    assign B = ~btnB;
    
    wire auto_entra, auto_sale;
    wire [2:0] count;
    wire lleno, vacio;
    wire persona;           // usado internamente, pero no conectado a salida

    // FSM de sensores
    fsm_sensores fsm (
        .clk(clk),
        .reset(rst),
        .a(A),
        .b(B),
        .auto_entra(auto_entra),
        .auto_sale(auto_sale),
        .persona(persona)
    );

    // Contador de autos
    contador_estacionamiento contador (
        .clk(clk),
        .reset(rst),
        .auto_entra(auto_entra),
        .auto_sale(auto_sale),
        .count(count),
        .lleno(lleno),
        .vacio(vacio)
    );

    // Asignación de LEDs
    assign leds[2:0] = count;  // 3 bits del contador
    assign leds[3]   = lleno;  // LED extra para "lleno"

endmodule

top-module/top-module_tb.v
`timescale 1ns / 1ps
`default_nettype none
`define DUMPSTR(x) `"x.vcd`"

module top_estacionamiento_tb;

    reg clk, reset;
    reg btnA, btnB;
    wire [3:0] leds;

    top_estacionamiento dut (
        .clk(clk),
        .reset(reset),
        .btnA(btnA),
        .btnB(btnB),
        .leds(leds)
    );

    // Clock de 10ns
    initial begin
        clk = 0;
        forever #5 clk = ~clk;
    end

    // Simulación de entrada de auto (btnA → ambos → btnB → sueltan)
    task auto_entrando;
    begin
        btnA = 0; btnB = 1; #10;
        btnA = 0; btnB = 0; #10;
        btnA = 1; btnB = 0; #10;
        btnA = 1; btnB = 1; #10;
    end
    endtask

    // Simulación de salida de auto (btnB → ambos → btnA → sueltan)
    task auto_saliendo;
    begin
        btnA = 1; btnB = 0; #10;
        btnA = 0; btnB = 0; #10;
        btnA = 0; btnB = 1; #10;
        btnA = 1; btnB = 1; #10;
    end
    endtask

    // Simulación de persona (pisa A o B, no pisa ambos, suelta)
    task persona_pasando_E;
    begin
        btnA = 0; btnB = 1; #10;
        btnA = 1; btnB = 1; #10;
        #10;
    end
    endtask

    task persona_pasando_S;
    begin
        btnA = 1; btnB = 0; #10;
        btnA = 1; btnB = 1; #10;
        #10;
    end
    endtask

    initial begin
        $dumpfile("top-module_tb.vcd");
        $dumpvars(0, top_estacionamiento_tb);

        // Inicialización   |   La logica de los botones es al revez
        btnA = 1; btnB = 1; reset = 0; #10;
        reset = 1;

        // Auto entra (contador = 1)
        auto_entrando();

        // Persona pasa primero por sensor A
        persona_pasando_E();

        // (contador = 2)
        auto_entrando();

        // Autos sale (contador = 0)
        repeat (2) auto_saliendo(); 

        // 7 autos entran (para ver LED "lleno")
        repeat (7) auto_entrando();

        // Auto más entra (no debería contar más)
        auto_entrando();

        // Auto sale (contador = 6)
        auto_saliendo();

        // Persona pasa primero por sensor B
        persona_pasando_S();

        // (contador = 3)
        repeat (3) auto_saliendo();

        // Finalizacion
        #30; 
        btnA = 1; btnB = 1; reset = 0;

        #30;
        $finish;
    end

endmodule

top-module/top-module_tb.vcd
$date
	Sat Jun 21 16:17:30 2025
$end
$version
	Icarus Verilog
$end
$timescale
	1ps
$end
$scope module top_estacionamiento_tb $end
$var wire 4 ! leds [3:0] $end
$var reg 1 " btnA $end
$var reg 1 # btnB $end
$var reg 1 $ clk $end
$var reg 1 % reset $end
$scope module dut $end
$var wire 1 & A $end
$var wire 1 ' B $end
$var wire 1 " btnA $end
$var wire 1 # btnB $end
$var wire 1 $ clk $end
$var wire 1 % reset $end
$var wire 1 ( rst $end
$var wire 1 ) vacio $end
$var wire 1 * persona $end
$var wire 1 + lleno $end
$var wire 4 , leds [3:0] $end
$var wire 3 - count [2:0] $end
$var wire 1 . auto_sale $end
$var wire 1 / auto_entra $end
$scope module contador $end
$var wire 1 $ clk $end
$var wire 1 ( reset $end
$var wire 1 ) vacio $end
$var wire 1 + lleno $end
$var wire 1 . auto_sale $end
$var wire 1 / auto_entra $end
$var reg 3 0 count [2:0] $end
$upscope $end
$scope module fsm $end
$var wire 1 & a $end
$var wire 1 ' b $end
$var wire 1 $ clk $end
$var wire 1 ( reset $end
$var parameter 3 1 E1 $end
$var parameter 3 2 E2 $end
$var parameter 3 3 E3 $end
$var parameter 3 4 EST_INICIAL $end
$var parameter 3 5 P $end
$var parameter 3 6 S1 $end
$var parameter 3 7 S2 $end
$var parameter 3 8 S3 $end
$var reg 1 / auto_entra $end
$var reg 1 . auto_sale $end
$var reg 3 9 estado [2:0] $end
$var reg 3 : next_estado [2:0] $end
$var reg 1 * persona $end
$upscope $end
$upscope $end
$scope task auto_entrando $end
$upscope $end
$scope task auto_saliendo $end
$upscope $end
$scope task persona_pasando_E $end
$upscope $end
$scope task persona_pasando_S $end
$upscope $end
$upscope $end
$enddefinitions $end
$comment Show the parameter values. $end
$dumpall
b111 8
b110 7
b101 6
b100 5
b0 4
b11 3
b10 2
b1 1
$end
#0
$dumpvars
b0 :
b0 9
b0 0
0/
0.
b0 -
b0 ,
0+
0*
1)
1(
0'
0&
0%
0$
1#
1"
b0 !
$end
#5000
1$
#10000
b1 :
1&
0(
0$
0"
1%
#15000
b1 9
1$
#20000
b10 :
1'
0$
0#
#25000
b10 9
1$
#30000
b11 :
0&
0$
1"
#35000
b11 9
1$
#40000
b0 :
0'
0$
1#
#45000
1/
b0 9
1$
#50000
b1 :
1&
0$
0"
#55000
0/
b1 9
0)
b1 !
b1 ,
b1 -
b1 0
1$
#60000
b100 :
0&
0$
1"
#65000
b0 :
1*
b100 9
1$
#70000
0$
#75000
0*
b0 9
1$
#80000
b1 :
1&
0$
0"
#85000
b1 9
1$
#90000
b10 :
1'
0$
0#
#95000
b10 9
1$
#100000
b11 :
0&
0$
1"
#105000
b11 9
1$
#110000
b0 :
0'
0$
1#
#115000
1/
b0 9
1$
#120000
b101 :
1'
0$
0#
#125000
b10 !
b10 ,
b10 -
b10 0
0/
b101 9
1$
#130000
b110 :
1&
0$
0"
#135000
b110 9
1$
#140000
b111 :
0'
0$
1#
#145000
b111 9
1$
#150000
b0 :
0&
0$
1"
#155000
1.
b0 9
1$
#160000
b101 :
1'
0$
0#
#165000
b1 !
b1 ,
b1 -
b1 0
0.
b101 9
1$
#170000
b110 :
1&
0$
0"
#175000
b110 9
1$
#180000
b111 :
0'
0$
1#
#185000
b111 9
1$
#190000
b0 :
0&
0$
1"
#195000
1.
b0 9
1$
#200000
b1 :
1&
0$
0"
#205000
1)
b0 !
b0 ,
b0 -
b0 0
0.
b1 9
1$
#210000
b10 :
1'
0$
0#
#215000
b10 9
1$
#220000
b11 :
0&
0$
1"
#225000
b11 9
1$
#230000
b0 :
0'
0$
1#
#235000
1/
b0 9
1$
#240000
b1 :
1&
0$
0"
#245000
0)
b1 !
b1 ,
b1 -
b1 0
0/
b1 9
1$
#250000
b10 :
1'
0$
0#
#255000
b10 9
1$
#260000
b11 :
0&
0$
1"
#265000
b11 9
1$
#270000
b0 :
0'
0$
1#
#275000
1/
b0 9
1$
#280000
b1 :
1&
0$
0"
#285000
b10 !
b10 ,
b10 -
b10 0
0/
b1 9
1$
#290000
b10 :
1'
0$
0#
#295000
b10 9
1$
#300000
b11 :
0&
0$
1"
#305000
b11 9
1$
#310000
b0 :
0'
0$
1#
#315000
1/
b0 9
1$
#320000
b1 :
1&
0$
0"
#325000
b11 !
b11 ,
b11 -
b11 0
0/
b1 9
1$
#330000
b10 :
1'
0$
0#
#335000
b10 9
1$
#340000
b11 :
0&
0$
1"
#345000
b11 9
1$
#350000
b0 :
0'
0$
1#
#355000
1/
b0 9
1$
#360000
b1 :
1&
0$
0"
#365000
b100 !
b100 ,
b100 -
b100 0
0/
b1 9
1$
#370000
b10 :
1'
0$
0#
#375000
b10 9
1$
#380000
b11 :
0&
0$
1"
#385000
b11 9
1$
#390000
b0 :
0'
0$
1#
#395000
1/
b0 9
1$
#400000
b1 :
1&
0$
0"
#405000
b101 !
b101 ,
b101 -
b101 0
0/
b1 9
1$
#410000
b10 :
1'
0$
0#
#415000
b10 9
1$
#420000
b11 :
0&
0$
1"
#425000
b11 9
1$
#430000
b0 :
0'
0$
1#
#435000
1/
b0 9
1$
#440000
b1 :
1&
0$
0"
#445000
b110 !
b110 ,
b110 -
b110 0
0/
b1 9
1$
#450000
b10 :
1'
0$
0#
#455000
b10 9
1$
#460000
b11 :
0&
0$
1"
#465000
b11 9
1$
#470000
b0 :
0'
0$
1#
#475000
1/
b0 9
1$
#480000
b1 :
1&
0$
0"
#485000
1+
b1111 !
b1111 ,
b111 -
b111 0
0/
b1 9
1$
#490000
b10 :
1'
0$
0#
#495000
b10 9
1$
#500000
b11 :
0&
0$
1"
#505000
b11 9
1$
#510000
b0 :
0'
0$
1#
#515000
1/
b0 9
1$
#520000
b101 :
1'
0$
0#
#525000
0/
b101 9
1$
#530000
b110 :
1&
0$
0"
#535000
b110 9
1$
#540000
b111 :
0'
0$
1#
#545000
b111 9
1$
#550000
b0 :
0&
0$
1"
#555000
1.
b0 9
1$
#560000
b101 :
1'
0$
0#
#565000
0+
b110 !
b110 ,
b110 -
b110 0
0.
b101 9
1$
#570000
b100 :
0'
0$
1#
#575000
b0 :
1*
b100 9
1$
#580000
0$
#585000
0*
b0 9
1$
#590000
b101 :
1'
0$
0#
#595000
b101 9
1$
#600000
b110 :
1&
0$
0"
#605000
b110 9
1$
#610000
b111 :
0'
0$
1#
#615000
b111 9
1$
#620000
b0 :
0&
0$
1"
#625000
1.
b0 9
1$
#630000
b101 :
1'
0$
0#
#635000
0.
b101 9
b101 !
b101 ,
b101 -
b101 0
1$
#640000
b110 :
1&
0$
0"
#645000
b110 9
1$
#650000
b111 :
0'
0$
1#
#655000
b111 9
1$
#660000
b0 :
0&
0$
1"
#665000
1.
b0 9
1$
#670000
b101 :
1'
0$
0#
#675000
0.
b101 9
b100 !
b100 ,
b100 -
b100 0
1$
#680000
b110 :
1&
0$
0"
#685000
b110 9
1$
#690000
b111 :
0'
0$
1#
#695000
b111 9
1$
#700000
b0 :
0&
0$
1"
#705000
1.
b0 9
1$
#710000
0$
#715000
0.
b11 !
b11 ,
b11 -
b11 0
1$
#720000
0$
#725000
1$
#730000
0$
#735000
1$
#740000
1)
b0 !
b0 ,
b0 -
b0 0
1(
0$
0%
